README.md
setup.py
kinton/__init__.py
kinton/ansible.py
kinton/ansible_config.py
kinton/aws.py
kinton/cloud.py
kinton/command_line.py
kinton/config_files.py
kinton/configuration.py
kinton/file_system.py
kinton/google.py
kinton/printer.py
kinton.egg-info/PKG-INFO
kinton.egg-info/SOURCES.txt
kinton.egg-info/dependency_links.txt
kinton.egg-info/entry_points.txt
kinton.egg-info/not-zip-safe
kinton.egg-info/requires.txt
kinton.egg-info/top_level.txt