Metadata-Version: 1.1
Name: kinton
Version: 0.1.4
Summary: This is the perfect tool if you want run the same tasks in servers in AWS and Google Cloud with only one comand.
Home-page: https://github.com/the-cocktail/kinton
Author: Jesus Sayar
Author-email: jesus.sayar@the-cocktail.com
License: MIT
Keywords: ansible infrastructure provisioning
Platform: UNKNOWN
Classifier: Development Status :: 4 - Beta
Classifier: License :: OSI Approved :: MIT License
Classifier: Programming Language :: Python
Classifier: Operating System :: Unix
Classifier: Intended Audience :: System Administrators
Classifier: Topic :: System :: Systems Administration
